gloomhaven/__init__.py
gloomhaven/constants.py
gloomhaven/deck.py
gloomhaven/mod_applier.py
gloomhaven/reader.py
gloomhaven/render.py
gloomhaven/templates/tables.html
gloomhaven-1.0.0.dist-info/LICENSE
gloomhaven-1.0.0.dist-info/WHEEL
gloomhaven-1.0.0.dist-info/METADATA
gloomhaven-1.0.0.dist-info/RECORD
