Metadata-Version: 2.1
Name: gloomhaven
Version: 1.0.0
Summary: Probability evaluation of Gloomhaven attack modifier decks
License: Apache 2.0
Author: Zachary Coleman
Author-email: zacharywcoleman@gmail.com
Requires-Python: >=3.8,<4.0
Classifier: License :: Other/Proprietary License
Classifier: Programming Language :: Python :: 3
Classifier: Programming Language :: Python :: 3.10
Classifier: Programming Language :: Python :: 3.8
Classifier: Programming Language :: Python :: 3.9
Provides-Extra: analyze
Requires-Dist: Jinja2 (>=3.1.2,<4.0.0)
Requires-Dist: PyYAML (>=6.0,<7.0)
Requires-Dist: dask[distributed] (>=2022.6.1,<2023.0.0); extra == "analyze"
Requires-Dist: dictdiffer (>=0.9.0,<0.10.0); extra == "analyze"
Requires-Dist: jupyter (>=1.0.0,<2.0.0); extra == "analyze"
Requires-Dist: matplotlib (>=3.5.2,<4.0.0); extra == "analyze"
Requires-Dist: pandas (>=1.4.3,<2.0.0); extra == "analyze"
